MetaRpcMT5/__init__.py
MetaRpcMT5/mrpc_mt5_error_pb2.py
MetaRpcMT5/mrpc_mt5_error_pb2_grpc.py
MetaRpcMT5/mt5_account.py
MetaRpcMT5/mt5_term_api_account_helper_pb2.py
MetaRpcMT5/mt5_term_api_account_helper_pb2_grpc.py
MetaRpcMT5/mt5_term_api_account_information_pb2.py
MetaRpcMT5/mt5_term_api_account_information_pb2_grpc.py
MetaRpcMT5/mt5_term_api_charts_pb2.py
MetaRpcMT5/mt5_term_api_charts_pb2_grpc.py
MetaRpcMT5/mt5_term_api_connection_pb2.py
MetaRpcMT5/mt5_term_api_connection_pb2_grpc.py
MetaRpcMT5/mt5_term_api_health_check_pb2.py
MetaRpcMT5/mt5_term_api_health_check_pb2_grpc.py
MetaRpcMT5/mt5_term_api_internal_charts_pb2.py
MetaRpcMT5/mt5_term_api_internal_charts_pb2_grpc.py
MetaRpcMT5/mt5_term_api_market_info_pb2.py
MetaRpcMT5/mt5_term_api_market_info_pb2_grpc.py
MetaRpcMT5/mt5_term_api_subscriptions_pb2.py
MetaRpcMT5/mt5_term_api_subscriptions_pb2_grpc.py
MetaRpcMT5/mt5_term_api_trade_functions_pb2.py
MetaRpcMT5/mt5_term_api_trade_functions_pb2_grpc.py
MetaRpcMT5/mt5_term_api_trading_helper_pb2.py
MetaRpcMT5/mt5_term_api_trading_helper_pb2_grpc.py
metarpcmt5-1.0.137.dist-info/METADATA
metarpcmt5-1.0.137.dist-info/WHEEL
metarpcmt5-1.0.137.dist-info/top_level.txt
metarpcmt5-1.0.137.dist-info/RECORD
